<?xml version="1.0" encoding="UTF-8"?>
<!--
Regeltjes:
- Plaatjes beginnen altijd met een hoofdletter
- Onderwerp voor plaatje.
 -->
<onderwerpen>
	<onderwerp name="Steden" image="Steden.jpg">
		<vraag>
			<tekst>Welk stad is dit?</tekst>
			<onderdelen>
				<onderdeel image="Steden_Athene.jpg">Athene</onderdeel>
				<onderdeel image="Steden_Berlijn.jpg">Berlijn</onderdeel>
				<onderdeel image="Steden_Brussel.jpg">Brussel</onderdeel>
				<onderdeel image="Steden_Dublin.jpg">Dublin</onderdeel>
				<onderdeel image="Steden_Kopenhagen.jpg">Kopenhagen</onderdeel>
				<onderdeel image="Steden_Monaco.jpg">Monaco</onderdeel>
				<onderdeel image="Steden_Oslo.jpg">Oslo</onderdeel>
				<onderdeel image="Steden_Parijs.jpg">Parijs</onderdeel>
				<onderdeel image="Steden_Rome.jpg">Rome</onderdeel>
			</onderdelen>
		</vraag>
	</onderwerp>
	<onderwerp name="Alcohol" image="Bier.jpg">
		<vraag>
			<tekst>Welk land is dit?</tekst>
			<onderdelen>
				<onderdeel image="Steden_Athene.jpg">Athene</onderdeel>
				<onderdeel image="Steden_Berlijn.jpg">Berlijn</onderdeel>
				<onderdeel image="Steden_Brussel.jpg">Brussel</onderdeel>
				<onderdeel image="Steden_Dublin.jpg">Dublin</onderdeel>
				<onderdeel image="Steden_Kopenhagen.jpg">Kopenhagen</onderdeel>
				<onderdeel image="Steden_Monaco.jpg">Monaco</onderdeel>
				<onderdeel image="Steden_Oslo.jpg">Oslo</onderdeel>
				<onderdeel image="Steden_Parijs.jpg">Parijs</onderdeel>
				<onderdeel image="Steden_Rome.jpg">Rome</onderdeel>
			</onderdelen>
		</vraag>
	</onderwerp>
</onderwerpen>